[ {
  "id" : {
    "queryId" : "Q_PRODCOOU_UG38",
    "version" : "1.0.0"
  },
  "name" : "ProductoQuery",
  "sqlWhere" : null,
  "customizationLayer" : 0,
  "customizationLayerDescription" : "ECU",
  "mainEntityId" : "EN_PRODUCTOO_408",
  "mainEntityVersion" : "1.0.0",
  "queryMembers" : [ {
    "alias" : "nombre",
    "attribute" : {
      "attributeId" : "AT58_NOMBREMG408",
      "autoGenerated" : false,
      "autoGeneratedStr" : "F",
      "columnName" : null,
      "customizationLayer" : 0,
      "customizationLayerDescription" : "ECU",
      "dataType" : "String",
      "entityPk" : {
        "entityId" : "EN_PRODUCTOO_408",
        "version" : "1.0.0"
      },
      "expression" : null,
      "falseValue" : null,
      "label" : null,
      "labelId" : null,
      "length" : 0,
      "listValues" : null,
      "name" : "nombre",
      "objectType" : null,
      "order" : 3,
      "pk" : false,
      "pkStr" : "F",
      "required" : false,
      "requiredStr" : "F",
      "transient" : false,
      "transientStr" : "F",
      "trueValue" : null
    },
    "customizationLayer" : 0,
    "customizationLayerDescription" : "",
    "defaultValue" : null,
    "defaultValueDataType" : null,
    "function" : null,
    "label" : null,
    "operator" : null,
    "order" : 3,
    "orderBy" : 0,
    "orderByDirection" : null,
    "queryMemberId" : "QM_PRODC88GOG826_03",
    "select" : true,
    "selectStr" : "T",
    "where" : false,
    "whereStr" : "F"
  }, {
    "alias" : "precio",
    "attribute" : {
      "attributeId" : "AT14_PRECIOHB408",
      "autoGenerated" : false,
      "autoGeneratedStr" : "F",
      "columnName" : null,
      "customizationLayer" : 0,
      "customizationLayerDescription" : "ECU",
      "dataType" : "Double",
      "entityPk" : {
        "entityId" : "EN_PRODUCTOO_408",
        "version" : "1.0.0"
      },
      "expression" : null,
      "falseValue" : null,
      "label" : null,
      "labelId" : null,
      "length" : 0,
      "listValues" : null,
      "name" : "precio",
      "objectType" : null,
      "order" : 4,
      "pk" : false,
      "pkStr" : "F",
      "required" : false,
      "requiredStr" : "F",
      "transient" : false,
      "transientStr" : "F",
      "trueValue" : null
    },
    "customizationLayer" : 0,
    "customizationLayerDescription" : "",
    "defaultValue" : null,
    "defaultValueDataType" : null,
    "function" : null,
    "label" : null,
    "operator" : null,
    "order" : 4,
    "orderBy" : 0,
    "orderByDirection" : null,
    "queryMemberId" : "QM_PRODC8GGGG791_04",
    "select" : true,
    "selectStr" : "T",
    "where" : false,
    "whereStr" : "F"
  }, {
    "alias" : "codigo",
    "attribute" : {
      "attributeId" : "AT45_CODIGODB408",
      "autoGenerated" : false,
      "autoGeneratedStr" : "F",
      "columnName" : null,
      "customizationLayer" : 0,
      "customizationLayerDescription" : "ECU",
      "dataType" : "String",
      "entityPk" : {
        "entityId" : "EN_PRODUCTOO_408",
        "version" : "1.0.0"
      },
      "expression" : null,
      "falseValue" : null,
      "label" : null,
      "labelId" : null,
      "length" : 0,
      "listValues" : null,
      "name" : "codigo",
      "objectType" : null,
      "order" : 2,
      "pk" : false,
      "pkStr" : "F",
      "required" : false,
      "requiredStr" : "F",
      "transient" : false,
      "transientStr" : "F",
      "trueValue" : null
    },
    "customizationLayer" : 0,
    "customizationLayerDescription" : "",
    "defaultValue" : null,
    "defaultValueDataType" : null,
    "function" : null,
    "label" : null,
    "operator" : null,
    "order" : 2,
    "orderBy" : 0,
    "orderByDirection" : null,
    "queryMemberId" : "QM_PRODC8U883898_02",
    "select" : true,
    "selectStr" : "T",
    "where" : false,
    "whereStr" : "F"
  }, {
    "alias" : "fechaCreacion",
    "attribute" : {
      "attributeId" : "AT82_FECHACER408",
      "autoGenerated" : false,
      "autoGeneratedStr" : "F",
      "columnName" : null,
      "customizationLayer" : 0,
      "customizationLayerDescription" : "ECU",
      "dataType" : "Date",
      "entityPk" : {
        "entityId" : "EN_PRODUCTOO_408",
        "version" : "1.0.0"
      },
      "expression" : null,
      "falseValue" : null,
      "label" : null,
      "labelId" : null,
      "length" : 0,
      "listValues" : null,
      "name" : "fechaCreacion",
      "objectType" : null,
      "order" : 6,
      "pk" : false,
      "pkStr" : "F",
      "required" : false,
      "requiredStr" : "F",
      "transient" : false,
      "transientStr" : "F",
      "trueValue" : null
    },
    "customizationLayer" : 0,
    "customizationLayerDescription" : "",
    "defaultValue" : null,
    "defaultValueDataType" : null,
    "function" : null,
    "label" : null,
    "operator" : null,
    "order" : 6,
    "orderBy" : 0,
    "orderByDirection" : null,
    "queryMemberId" : "QM_PRODCOOO3U688_06",
    "select" : true,
    "selectStr" : "T",
    "where" : false,
    "whereStr" : "F"
  }, {
    "alias" : "idProducto",
    "attribute" : {
      "attributeId" : "AT68_IDPRODTU408",
      "autoGenerated" : false,
      "autoGeneratedStr" : "F",
      "columnName" : null,
      "customizationLayer" : 0,
      "customizationLayerDescription" : "ECU",
      "dataType" : "Integer",
      "entityPk" : {
        "entityId" : "EN_PRODUCTOO_408",
        "version" : "1.0.0"
      },
      "expression" : null,
      "falseValue" : null,
      "label" : null,
      "labelId" : null,
      "length" : 0,
      "listValues" : null,
      "name" : "idProducto",
      "objectType" : null,
      "order" : 1,
      "pk" : false,
      "pkStr" : "F",
      "required" : false,
      "requiredStr" : "F",
      "transient" : false,
      "transientStr" : "F",
      "trueValue" : null
    },
    "customizationLayer" : 0,
    "customizationLayerDescription" : "",
    "defaultValue" : null,
    "defaultValueDataType" : null,
    "function" : null,
    "label" : null,
    "operator" : null,
    "order" : 1,
    "orderBy" : 0,
    "orderByDirection" : null,
    "queryMemberId" : "QM_PRODCOOOUU945_01",
    "select" : true,
    "selectStr" : "T",
    "where" : false,
    "whereStr" : "F"
  } ],
  "customEvents" : [ {
    "executionType" : 3,
    "customEventId" : "CEQY_130_Q_PRODCOOU_UG38_980",
    "filter" : null,
    "customizationLayer" : 0,
    "customizationLayerDescription" : "ECU",
    "queryEventType" : {
      "eventId" : 130,
      "name" : "ExecuteQuery",
      "description" : "Sobreescribe la ejecución de un Query"
    },
    "eventActions" : [ {
      "actionId" : "CUSTOM",
      "actionType" : "CUSTOM",
      "actionArgs" : [ ]
    } ],
    "customizedEventType" : "INHERITED",
    "id" : null,
    "eventId" : 130
  } ],
  "isAutomatic" : false,
  "mainEntityModule" : "FCTRC"
} ]